silentisai/__init__.py
silentisai/run.py
silentisai/silentis.py
silentis_ai-1.2.3.dist-info/LICENSE
silentis_ai-1.2.3.dist-info/METADATA
silentis_ai-1.2.3.dist-info/WHEEL
silentis_ai-1.2.3.dist-info/entry_points.txt
silentis_ai-1.2.3.dist-info/top_level.txt
silentis_ai-1.2.3.dist-info/RECORD
