Metadata-Version: 2.1
Name: silentis-ai
Version: 1.2.3
Summary: Silentis AI - A powerful AI assistant plugin.
Home-page: https://github.com/Silentisai/Silentis
Author: Silentis Team
Author-email: support@silentis.ai
Classifier: Programming Language :: Python :: 3
Classifier: License :: OSI Approved :: MIT License
Classifier: Operating System :: OS Independent
Requires-Python: >=3.7
License-File: LICENSE
Requires-Dist: flask
Requires-Dist: requests
Requires-Dist: llama-cpp-python
Requires-Dist: psutil
Requires-Dist: flask-cors
